bums/__init__.py
bums/chain.py
bums/const.py
bums/dates.py
bums/exc.py
bums/logic.py
bums/structs.py
bums/version.py
bums-1.0.0rc1.dist-info/METADATA
bums-1.0.0rc1.dist-info/WHEEL
bums-1.0.0rc1.dist-info/top_level.txt
bums-1.0.0rc1.dist-info/RECORD
